synko/__init__.py
synko/app.py
synko/constants.py
synko/main.py
synko/utils.py
synko-0.9.0.dist-info/LICENSE
synko-0.9.0.dist-info/METADATA
synko-0.9.0.dist-info/WHEEL
synko-0.9.0.dist-info/entry_points.txt
synko-0.9.0.dist-info/top_level.txt
synko-0.9.0.dist-info/RECORD
