Metadata-Version: 2.1
Name: synko
Version: 0.9.0
Summary: Sync application configurations and settings across multiple multiplatform devices. Currently supports linux and osx, working in progress for windows
Home-page: https://github.com/souvikinator/synko
Author: souvikinator
Author-email: souvikat001@gmail.com
License: GPL-3.0
Platform: UNKNOWN
Classifier: Development Status :: 4 - Beta
Classifier: License :: OSI Approved :: GNU General Public License v3 (GPLv3)
Classifier: Operating System :: POSIX :: Linux
Classifier: Operating System :: MacOS
Classifier: Programming Language :: Python :: 3
Classifier: Programming Language :: Python :: 3.4
Classifier: Programming Language :: Python :: 3.5
Classifier: Programming Language :: Python :: 3.6
Classifier: Programming Language :: Python :: 3.7
Classifier: Intended Audience :: Developers
Classifier: Intended Audience :: End Users/Desktop
Classifier: Intended Audience :: System Administrators
Classifier: Topic :: System :: Installation/Setup
Classifier: Topic :: System :: Archiving :: Backup
Classifier: Topic :: System :: Operating System
Classifier: Topic :: Documentation
Classifier: Topic :: Utilities
Requires-Python: >=3
Requires-Dist: click
Requires-Dist: inquirer
Requires-Dist: pyyaml
